{
  "isSuccess": true,
  "data": [
    {
      "pageNumber": 137,
      "sectionNumber": 1,
      "hasTextContent": true,
      "hasImageContent": true,
      "paragList": [
        {
          "paragraphId": 631644672,
          "paragNumber": 1,
          "tocNumber": 0,
          "text": "<p id=\"488\"><page number=\"137\"/><heading level=\"3\">فوائد الهواء الأخرى</heading></p>"
        },
        {
          "paragraphId": 631644673,
          "paragNumber": 2,
          "tocNumber": 0,
          "text": "<p id=\"489\"><format class=\"M\">قال عليه السلام: و حسبك بهذا النسيم المسمى هواء عبرة و ما فيه من المصالح فانه حياة هذه الابدان و الممسك لها من داخل بما يستنشق منه من خارج بما يباشر من روحه،</format></p>"
        },
        {
          "paragraphId": 631644674,
          "paragNumber": 3,
          "tocNumber": 0,
          "text": "<p id=\"490\"><format class=\"sharh\">الهواء عنصر هام لا غنى لكل كائن حى عنه اذ قد يصبر الحيوان على الجوع و العطش أياما و لكن لا يصبر عن الهواء دقائق، و قد تقدم ذكر بعض فوائده و هنا نذكر ما تقدم منها و ما لم نذكرها فنقول:</format></p>"
        },
        {
          "paragraphId": 631644675,
          "paragNumber": 4,
          "tocNumber": 0,
          "text": "<p id=\"491\"><format class=\"sharh\">أولا - التنفس و هو عبارة عن عملية الشهيق و الزفير لجذب النسيم (الاكسجين) الى داخل الرئة ثم الى الدم بالشهيق و دفع ما احترق من الاجزاء المختلطة مع الدم الى الخارج (الكربون) بالزفير فان هذا النسيم هو مصدر جميع مظاهر الطاقة و القوى الحيوية التى تعيش عليها الحيوانات و النباتات.</format></p>"
        },
        {
          "paragraphId": 631644676,
          "paragNumber": 5,
          "tocNumber": 0,
          "text": "<p id=\"492\"><format class=\"sharh\">و لذلك قال عليه السلام: (فانه حياة هذه الابدان) ثم بين كيفية التنفس بقوله عليه السلام (و الممسك لها من داخل بما يستنشق منه من خارج بما يباشر من روحه) أي أن هذا النسيم المستنشق من الخارج يمسك الاعضاء الداخلية و ينقيها من المواد المحترقة (الكربون) فيكون هذا النقاء و التصفية بالتنفس هو </format><page number=\"138\"/><format class=\"M\">و فيه هذه الاصوات فيؤدى البعد البعيد، و هو الحامل لهذه الارواح ينقلها من موضع الى موضع. الا ترى كيف تأتيك الرائحة من حيث تهب الريح فكذلك الصوت، و هو القابل لهذا</format></p>"
        }
      ],
      "taliqehList": null,
      "footnoteList": null,
      "pageValue": "137",
      "isFreeStudy": true,
      "requestedContentType": "text",
      "providedContentType": "text",
      "isEmpty": false,
      "html": "<div class=\"CODE\">\n  <p id=\"p488\" paragraph-id=\"488\" class=\" G\">\n    <span class=\"GPA0 bookPage PageNo137\">137</span>\n    <strong style=\"0\" class=\"h-3 03\">فوائد الهواء الأخرى</strong>\n  </p>\n  <p id=\"p489\" paragraph-id=\"489\" class=\" G\">\n    <span class=\"M\">قال عليه السلام: و حسبك بهذا النسيم المسمى هواء عبرة و ما فيه من المصالح فانه حياة هذه الابدان و الممسك لها من داخل بما يستنشق منه من خارج بما يباشر من روحه،</span>\n  </p>\n  <p id=\"p490\" paragraph-id=\"490\" class=\" G\">\n    <span class=\"sharh\">الهواء عنصر هام لا غنى لكل كائن حى عنه اذ قد يصبر الحيوان على الجوع و العطش أياما و لكن لا يصبر عن الهواء دقائق، و قد تقدم ذكر بعض فوائده و هنا نذكر ما تقدم منها و ما لم نذكرها فنقول:</span>\n  </p>\n  <p id=\"p491\" paragraph-id=\"491\" class=\" G\">\n    <span class=\"sharh\">أولا - التنفس و هو عبارة عن عملية الشهيق و الزفير لجذب النسيم (الاكسجين) الى داخل الرئة ثم الى الدم بالشهيق و دفع ما احترق من الاجزاء المختلطة مع الدم الى الخارج (الكربون) بالزفير فان هذا النسيم هو مصدر جميع مظاهر الطاقة و القوى الحيوية التى تعيش عليها الحيوانات و النباتات.</span>\n  </p>\n  <p id=\"p492\" paragraph-id=\"492\" class=\" G\">\n    <span class=\"sharh\">و لذلك قال عليه السلام: (فانه حياة هذه الابدان) ثم بين كيفية التنفس بقوله عليه السلام (و الممسك لها من داخل بما يستنشق منه من خارج بما يباشر من روحه) أي أن هذا النسيم المستنشق من الخارج يمسك الاعضاء الداخلية و ينقيها من المواد المحترقة (الكربون) فيكون هذا النقاء و التصفية بالتنفس هو </span>\n  </p>\n</div>",
      "bookPageVisitLogId": "A55FBC43-826E-4777-A949-50B84E14FBB4",
      "validation": {
        "code": 1,
        "type": "successful",
        "message": "محتوا در دسترس می باشد -  کتاب یا محدوده رایگان"
      }
    }
  ],
  "totalCount": 1,
  "statusCode": 200,
  "message": "OK",
  "exception": null,
  "validationMessages": null
}