{
  "isSuccess": true,
  "data": [
    {
      "pageNumber": 182,
      "sectionNumber": 1,
      "hasTextContent": true,
      "hasImageContent": true,
      "paragList": [
        {
          "paragraphId": 687849387,
          "paragNumber": 1,
          "tocNumber": 0,
          "text": "<p id=\"2089\"><format class=\"hadith\" who=\"9|8\" Id=\"609\" RevayatIndex=\"619\"><format class=\"sanadHadith\">وَ <format class=\"G\">عَنْهُ‌</format>، عَنْ <format class=\"G\">مُحَمَّدِ بْنِ مُوسَى</format>، عَنْ <format class=\"G\">عَلِيِّ بْنِ اَلْحَسَنِ اَلْهَمْدَانِيِّ‌</format>، عَنْ <format class=\"G\">مُحَمَّدِ بْنِ‌<page number=\"182\"/> عَمْرِو بْنِ إِبْرَاهِيمَ‌</format>، عَنْ <format class=\"Y\"><format class=\"maasoom\" maasoomNo=\"9\">أَبِي جَعْفَرٍ</format></format>، أَوْ <format class=\"Y\"><format class=\"maasoom\" maasoomNo=\"8\">أَبِي اَلْحَسَنِ (عَلَيْهِمَا اَلسَّلاَمُ‌)</format></format> - اَلْوَهْمُ مِنْ <format class=\"G\">مُحَمَّدِ بْنِ مُوسَى </format>- قَالَ‌:</format></format></p>"
        },
        {
          "paragraphId": 687849388,
          "paragNumber": 2,
          "tocNumber": 0,
          "text": "<p id=\"2090\"><format class=\"hadith\" who=\"9|8\" Id=\"609\" RevayatIndex=\"619\">ذُكِرَ اَلسَّذَابُ فَقَالَ‌: أَمَا إِنَّ فِيهِ مَنَافِعَ‌، زِيَادَةً فِي اَلْعَقْلِ وَ تَوْفِيراً فِي اَلدِّمَاغِ‌، غَيْرَ أَنَّهُ يُنَتِّنُ مَاءَ اَلظَّهْرِ.</format></p>"
        },
        {
          "paragraphId": 687849389,
          "paragNumber": 3,
          "tocNumber": 0,
          "text": "<p id=\"2091\"><format class=\"hadith\" who=\"9|8\" Id=\"609\" RevayatIndex=\"619\">وَ رُوِيَ‌: أَنَّهُ جَيِّدٌ لِوَجَعِ اَلْأُذُنِ‌.</format></p>"
        },
        {
          "paragraphId": 687849390,
          "paragNumber": 4,
          "tocNumber": 0,
          "text": "<p id=\"2092\"><format class=\"hadith\" who=\"\" Id=\"609\" RevayatIndex=\"\"><format class=\"sanadHadith\">وَ فِي اَلْمَحَاسِنِ‌:</format> نَحْوَهُ‌.</format></p>"
        },
        {
          "paragraphId": 687849391,
          "paragNumber": 5,
          "tocNumber": 0,
          "text": "<p id=\"2093\"><format class=\"hadith\" who=\"8\" Id=\"610\" RevayatIndex=\"620\"><format class=\"sanadHadith\"><format class=\"K\">اَلْمَكَارِمِ‌</format>: عَنِ <format class=\"Y\"><format class=\"maasoom\" maasoomNo=\"8\">اَلرِّضَا (عَلَيْهِ اَلسَّلاَمُ‌)</format></format>، قَالَ‌:</format> اَلسَّذَابُ يَزِيدُ فِي اَلْعَقْلِ‌، غَيْرَ أَنَّهُ يَنْثُرُ مَاءَ اَلظَّهْرِ.</format></p>"
        },
        {
          "paragraphId": 687849392,
          "paragNumber": 6,
          "tocNumber": 0,
          "text": "<p id=\"2094\"><format class=\"hadith\" who=\"14\" Id=\"611\" RevayatIndex=\"621\"><format class=\"sanadHadith\">وَ عَنِ اَلْفِرْدَوْسِ‌، عَنْ عَائِشَةَ‌، عَنِ اَلنَّبِيِّ صَلَّى اَللَّهُ عَلَيْهِ وَ آلِهِ قَالَ‌:</format> مَنْ أَكَلَ اَلسَّذَابَ‌، وَ نَامَ عَلَيْهِ‌، نَامَ آمِناً مِنَ اَلدَّاءِ‌، وَ اَلدُّبَيْلَةِ‌، وَ ذَاتِ اَلْجَنْبِ‌.</format></p>"
        },
        {
          "paragraphId": 687849393,
          "paragNumber": 7,
          "tocNumber": 0,
          "text": "<p id=\"2095\"><heading level=\"2\">باب ما جاء في <format class=\"VD\">الجرجير </format></heading></p>"
        },
        {
          "paragraphId": 687849394,
          "paragNumber": 8,
          "tocNumber": 0,
          "text": "<p id=\"2096\"><format class=\"hadith\" who=\"6\" Id=\"612\" RevayatIndex=\"622\"><format class=\"sanadHadith\"><format class=\"K\">اَلْكَافِي</format>: <format class=\"G\">اَلْعِدَّةُ‌</format>، عَنْ <format class=\"G\">أَحْمَدَ بْنِ أَبِي عَبْدِ اَللَّهِ‌</format>، عَنْ <format class=\"G\">مُحَمَّدِ بْنِ عِيسَى</format>، وَ <format class=\"G\">غَيْرِهِ‌</format>، عَنْ <format class=\"G\">قُتَيْبَةَ اَلْأَعْشَى </format>- أَوْ قَالَ‌: <format class=\"G\">قُتَيْبَةِ بْنِ مِهْرَانَ </format>- عَنْ <format class=\"G\">حَمَّادِ بْنِ زَكَرِيَّا</format> عَنْ <format class=\"Y\"><format class=\"maasoom\" maasoomNo=\"6\">أَبِي عَبْدِ اَللَّهِ (عَلَيْهِ اَلسَّلاَمُ‌)</format></format> قَالَ‌:</format></format></p>"
        },
        {
          "paragraphId": 687849395,
          "paragNumber": 9,
          "tocNumber": 0,
          "text": "<p id=\"2097\"><format class=\"hadith\" who=\"6\" Id=\"612\" RevayatIndex=\"622\">مَا تَضَلَّعَ‌<lfootnote noteId=\"98\">1</lfootnote> اَلرَّجُلُ مِنَ اَلْجِرْجِيرِ، بَعْدَ أَنْ يُصَلِّيَ اَلْعِشَاءَ اَلْآخِرَةَ‌، فَبَاتَ تِلْكَ اَللَّيْلَةَ إِلاَّ وَ نَفْسُهُ تُنَازِعُهُ إِلَى اَلْجُذَامِ‌. وَ فِي بَعْضِ اَلنُّسَخِ اَلْحَرَامِ‌.</format></p>"
        },
        {
          "paragraphId": 687849396,
          "paragNumber": 10,
          "tocNumber": 0,
          "text": "<p id=\"2098\"><format class=\"hadith\" who=\"6\" Id=\"613\" RevayatIndex=\"623\"><format class=\"sanadHadith\">وَ عَنْ عَلِيِّ بْنِ إِبْرَاهِيمَ‌، عَنْ أَبِيهِ‌، عَنِ اَلنَّوْفَلِيِّ أَوْ غَيْرِهِ‌، عَنِ اَلسَّكُونِيِّ‌، عَنْ أَبِي عَبْدِ اَللَّهِ (عَلَيْهِ اَلسَّلاَمُ‌)، قَالَ‌:</format></format></p>"
        },
        {
          "paragraphId": 687849397,
          "paragNumber": 11,
          "tocNumber": 0,
          "text": "<p id=\"2099\"><format class=\"hadith\" who=\"6\" Id=\"613\" RevayatIndex=\"623\">مَنْ أَكَلَ اَلْجِرْجِيرَ بِاللَّيْلِ‌، ضَرَبَ عَلَيْهِ عِرْقُ اَلْجُذَامِ‌، وَ بَاتَ يَنْزِفُ فِي اَلدَّمِ‌.</format></p>"
        },
        {
          "paragraphId": 687849398,
          "paragNumber": 12,
          "tocNumber": 0,
          "text": "<p id=\"2100\"><page number=\"183\"/>بيان: في (ينزف) على البناء للمفعول، و بنزفه الدم: إذا خرج منه دم كثير، حتى يضعف، فهو نزيف و منزوف.</p>"
        }
      ],
      "taliqehList": null,
      "footnoteList": [
        {
          "footnoteId": 687851731,
          "text": "<footnote id=\"98\"><page number=\"182\"/><mnote>(1)</mnote> شرب حتّى تضلّع: أي أكثر من الشراب حتّى ملأ جنبيه و أضلاعه و هي للمبالغة.</footnote>"
        }
      ],
      "pageValue": "182",
      "isFreeStudy": true,
      "requestedContentType": "text",
      "providedContentType": "text",
      "isEmpty": false,
      "html": "<div class=\"CODE\">\n  <p id=\"p2089\" paragraph-id=\"2089\" class=\" G\">\n    <span class=\"hadith\">\n      <span class=\"sanadHadith\">\n        <span class=\"G\">\n          <span class=\"GPA0 bookPage PageNo182\">182</span> عَمْرِو بْنِ إِبْرَاهِيمَ‌</span>، عَنْ <span class=\"Y\"><span class=\"maasoom\">أَبِي جَعْفَرٍ</span></span>، أَوْ <span class=\"Y\"><span class=\"maasoom\">أَبِي اَلْحَسَنِ (عَلَيْهِمَا اَلسَّلاَمُ‌)</span></span> - اَلْوَهْمُ مِنْ <span class=\"G\">مُحَمَّدِ بْنِ مُوسَى </span>- قَالَ‌:</span>\n    </span>\n  </p>\n  <p id=\"p2090\" paragraph-id=\"2090\" class=\" G\">\n    <span class=\"hadith\">ذُكِرَ اَلسَّذَابُ فَقَالَ‌: أَمَا إِنَّ فِيهِ مَنَافِعَ‌، زِيَادَةً فِي اَلْعَقْلِ وَ تَوْفِيراً فِي اَلدِّمَاغِ‌، غَيْرَ أَنَّهُ يُنَتِّنُ مَاءَ اَلظَّهْرِ.</span>\n  </p>\n  <p id=\"p2091\" paragraph-id=\"2091\" class=\" G\">\n    <span class=\"hadith\">وَ رُوِيَ‌: أَنَّهُ جَيِّدٌ لِوَجَعِ اَلْأُذُنِ‌.</span>\n  </p>\n  <p id=\"p2092\" paragraph-id=\"2092\" class=\" G\">\n    <span class=\"hadith\">\n      <span class=\"sanadHadith\">وَ فِي اَلْمَحَاسِنِ‌:</span> نَحْوَهُ‌.</span>\n  </p>\n  <p id=\"p2093\" paragraph-id=\"2093\" class=\" G\">\n    <span class=\"hadith\">\n      <span class=\"sanadHadith\">\n        <span class=\"K\">اَلْمَكَارِمِ‌</span>: عَنِ <span class=\"Y\"><span class=\"maasoom\">اَلرِّضَا (عَلَيْهِ اَلسَّلاَمُ‌)</span></span>، قَالَ‌:</span> اَلسَّذَابُ يَزِيدُ فِي اَلْعَقْلِ‌، غَيْرَ أَنَّهُ يَنْثُرُ مَاءَ اَلظَّهْرِ.</span>\n  </p>\n  <p id=\"p2094\" paragraph-id=\"2094\" class=\" G\">\n    <span class=\"hadith\">\n      <span class=\"sanadHadith\">وَ عَنِ اَلْفِرْدَوْسِ‌، عَنْ عَائِشَةَ‌، عَنِ اَلنَّبِيِّ صَلَّى اَللَّهُ عَلَيْهِ وَ آلِهِ قَالَ‌:</span> مَنْ أَكَلَ اَلسَّذَابَ‌، وَ نَامَ عَلَيْهِ‌، نَامَ آمِناً مِنَ اَلدَّاءِ‌، وَ اَلدُّبَيْلَةِ‌، وَ ذَاتِ اَلْجَنْبِ‌.</span>\n  </p>\n  <p id=\"p2095\" paragraph-id=\"2095\" class=\" G\">\n    <strong style=\"0\" class=\"h-2 02\">باب ما جاء في <span class=\"VD\">الجرجير </span></strong>\n  </p>\n  <p id=\"p2096\" paragraph-id=\"2096\" class=\" G\">\n    <span class=\"hadith\">\n      <span class=\"sanadHadith\">\n        <span class=\"K\">اَلْكَافِي</span>: <span class=\"G\">اَلْعِدَّةُ‌</span>، عَنْ <span class=\"G\">أَحْمَدَ بْنِ أَبِي عَبْدِ اَللَّهِ‌</span>، عَنْ <span class=\"G\">مُحَمَّدِ بْنِ عِيسَى</span>، وَ <span class=\"G\">غَيْرِهِ‌</span>، عَنْ <span class=\"G\">قُتَيْبَةَ اَلْأَعْشَى </span>- أَوْ قَالَ‌: <span class=\"G\">قُتَيْبَةِ بْنِ مِهْرَانَ </span>- عَنْ <span class=\"G\">حَمَّادِ بْنِ زَكَرِيَّا</span> عَنْ <span class=\"Y\"><span class=\"maasoom\">أَبِي عَبْدِ اَللَّهِ (عَلَيْهِ اَلسَّلاَمُ‌)</span></span> قَالَ‌:</span>\n    </span>\n  </p>\n  <p id=\"p2097\" paragraph-id=\"2097\" class=\" G\">\n    <span class=\"hadith\">مَا تَضَلَّعَ‌<span><sup><a class=\"NewFn\" href=\"#footnote98\" title=\"(1)  شرب حتّى تضلّع: أي أكثر من الشراب حتّى ملأ جنبيه و أضلاعه و هي للمبالغة.\">1</a></sup></span> اَلرَّجُلُ مِنَ اَلْجِرْجِيرِ، بَعْدَ أَنْ يُصَلِّيَ اَلْعِشَاءَ اَلْآخِرَةَ‌، فَبَاتَ تِلْكَ اَللَّيْلَةَ إِلاَّ وَ نَفْسُهُ تُنَازِعُهُ إِلَى اَلْجُذَامِ‌. وَ فِي بَعْضِ اَلنُّسَخِ اَلْحَرَامِ‌.</span>\n  </p>\n  <p id=\"p2098\" paragraph-id=\"2098\" class=\" G\">\n    <span class=\"hadith\">\n      <span class=\"sanadHadith\">وَ عَنْ عَلِيِّ بْنِ إِبْرَاهِيمَ‌، عَنْ أَبِيهِ‌، عَنِ اَلنَّوْفَلِيِّ أَوْ غَيْرِهِ‌، عَنِ اَلسَّكُونِيِّ‌، عَنْ أَبِي عَبْدِ اَللَّهِ (عَلَيْهِ اَلسَّلاَمُ‌)، قَالَ‌:</span>\n    </span>\n  </p>\n  <p id=\"p2099\" paragraph-id=\"2099\" class=\" G\">\n    <span class=\"hadith\">مَنْ أَكَلَ اَلْجِرْجِيرَ بِاللَّيْلِ‌، ضَرَبَ عَلَيْهِ عِرْقُ اَلْجُذَامِ‌، وَ بَاتَ يَنْزِفُ فِي اَلدَّمِ‌.</span>\n  </p>\n  <p id=\"p2100\" paragraph-id=\"2100\" class=\" G\" />\n  <hr class=\"footnoteLine\" />\n  <span>\n    <div class=\"footnote OriginalDigit\" id=\"footnote98\" footnote-id=\"98\">(1) <page number=\"182\" /> شرب حتّى تضلّع: أي أكثر من الشراب حتّى ملأ جنبيه و أضلاعه و هي للمبالغة.</div>\n  </span>\n</div>",
      "bookPageVisitLogId": "43A69DF6-D4E2-428D-ABA2-33A06D7C9DE9",
      "validation": {
        "code": 1,
        "type": "successful",
        "message": "محتوا در دسترس می باشد -  کتاب یا محدوده رایگان"
      }
    }
  ],
  "totalCount": 1,
  "statusCode": 200,
  "message": "OK",
  "exception": null,
  "validationMessages": null
}