{
  "isSuccess": true,
  "data": [
    {
      "pageNumber": 76,
      "sectionNumber": 1,
      "hasTextContent": true,
      "hasImageContent": true,
      "paragList": [
        {
          "paragraphId": 687848270,
          "paragNumber": 1,
          "tocNumber": 0,
          "text": "<p id=\"870\"><format class=\"hadith\" who=\"6\" Id=\"125\" RevayatIndex=\"127\"><page number=\"76\"/>«إِنَّ اَلرَّجُلَ يَقُولُ‌: حُمِمْتُ اَلْيَوْمَ‌، وَ سَهِرْتُ اَلْبَارِحَةَ‌، وَ قَدْ صَدَقَ‌، وَ لَيْسَ هَذَا شَكَاةً‌، وَ إِنَّمَا اَلشَّكْوَى أَنْ يَقُولَ‌: لَقَدِ اُبْتُلِيتُ بِمَا لَمْ يُبْتَلَ بِهِ أَحَدٌ، وَ يَقُولَ‌: لَقَدْ أَصَابَنِي مَا لَمْ يُصِبْ أَحَداً، وَ لَيْسَتِ اَلشَّكْوَى أَنْ يَقُولَ‌: سَهِرْتُ اَلْبَارِحَةَ وَ حُمِمْتُ اَلْيَوْمَ‌، وَ نَحْوَ هَذَا».</format></p>"
        },
        {
          "paragraphId": 687848271,
          "paragNumber": 2,
          "tocNumber": 0,
          "text": "<p id=\"871\"><format class=\"hadith\" who=\"\" Id=\"125\" RevayatIndex=\"\"><format class=\"sanadHadith\">مَعَانِي اَلْأَخْبَارِ: عَنْ جَعْفَرِ بْنِ مُحَمَّدِ بْنِ مَسْرُورٍ، عَنِ اَلْحُسَيْنِ بْنُ مُحَمَّدِ بْنِ عَامِرٍ، عَنْ عَمِّهِ عَبْدِ اَللَّهِ بْنِ عَامِرٍ، عَنْ مُحَمَّدِ بْنِ أَبِي عُمَيْرٍ:</format> مِثْلَهُ‌.</format></p>"
        },
        {
          "paragraphId": 687848272,
          "paragNumber": 3,
          "tocNumber": 0,
          "text": "<p id=\"872\"><format class=\"hadith\" who=\"6\" Id=\"126\" RevayatIndex=\"128\"><format class=\"sanadHadith\">وَ عَنْ أَبِيهِ‌، عَنْ سَعْدٍ، عَنْ أَحْمَدَ بْنِ مُحَمَّدٍ، عَنْ أَبِيهِ‌، عَنْ حَمَّادِ بْنِ عِيسَى، عَنْ رَجُلٍ‌، عَنْ أَبِي عَبْدِ اَللَّهِ (عَلَيْهِ اَلسَّلاَمُ‌) قَالَ‌:</format></format></p>"
        },
        {
          "paragraphId": 687848273,
          "paragNumber": 4,
          "tocNumber": 0,
          "text": "<p id=\"873\"><format class=\"hadith\" who=\"6\" Id=\"126\" RevayatIndex=\"128\">«لَيْسَ اَلشِّكَايَةُ أَنْ يَقُولَ اَلرَّجُلُ‌: مَرِضْتُ اَلْبَارِحَةَ‌، وَ وُعِكْتُ اَلْبَارِحَةَ‌، وَ لَكِنَّ اَلشِّكَايَةَ أَنْ يَقُولَ‌: اُبْتُلِيتُ بِمَا لَمْ يُبْتَلَ بِهِ أَحَدٌ!</format></p>"
        },
        {
          "paragraphId": 687848274,
          "paragNumber": 5,
          "tocNumber": 0,
          "text": "<p id=\"874\"><format class=\"hadith\" who=\"13,6\" Id=\"127\" RevayatIndex=\"129\"><format class=\"sanadHadith\"><format class=\"K\">اَلْكَافِي</format>: <format class=\"G\">اَلْعِدَّةُ‌</format>، عَنْ <format class=\"G\">سَهْلِ بْنِ زِيَادٍ</format>، عَنِ <format class=\"G\">اِبْنِ مَحْبُوبٍ‌</format>، عَنْ <format class=\"G\">عَبْدِ اَلْحَمِيدِ</format>، عَنْ <format class=\"Y\"><format class=\"maasoom\" maasoomNo=\"6\">أَبِي عَبْدِ اَللَّهِ (عَلَيْهِ اَلسَّلاَمُ‌)</format></format>، قَالَ‌:</format></format></p>"
        },
        {
          "paragraphId": 687848275,
          "paragNumber": 6,
          "tocNumber": 0,
          "text": "<p id=\"875\"><format class=\"hadith\" who=\"13,6\" Id=\"127\" RevayatIndex=\"129\">«إِذَا صَعِدَ مَلَكَا اَلْعَبْدِ اَلْمَرِيضِ إِلَى اَلسَّمَاءِ‌، عِنْدَ كُلِّ مَسَاءٍ‌، يَقُولُ اَلرَّبُّ‌:</format></p>"
        },
        {
          "paragraphId": 687848276,
          "paragNumber": 7,
          "tocNumber": 0,
          "text": "<p id=\"876\"><format class=\"hadith\" who=\"13,6\" Id=\"127\" RevayatIndex=\"129\">«مَا ذَا كَتَبْتُمَا لِعَبْدِي فِي مَرَضِهِ؟».</format></p>"
        },
        {
          "paragraphId": 687848277,
          "paragNumber": 8,
          "tocNumber": 0,
          "text": "<p id=\"877\"><format class=\"hadith\" who=\"13,6\" Id=\"127\" RevayatIndex=\"129\">فَيَقُولاَنِ‌: «اَلشِّكَايَةَ‌».</format></p>"
        },
        {
          "paragraphId": 687848278,
          "paragNumber": 9,
          "tocNumber": 0,
          "text": "<p id=\"878\"><format class=\"hadith\" who=\"13,6\" Id=\"127\" RevayatIndex=\"129\">فَيَقُولُ‌: «مَا أَنْصَفْتُ عَبْدِي أَنْ حَبَسْتُهُ فِي حَبْسٍ مِنْ حَبْسِي ثُمَّ أَمْنَعُهُ اَلشِّكَايَةَ‌! اُكْتُبَا لِعَبْدِي مِثْلَ مَا كُنْتُمَا تَكْتُبَانِ لَهُ مِنَ اَلْخَيْرِ فِي صِحَّتِهِ‌، وَ لاَ تَكْتُبَا عَلَيْهِ سَيِّئَةً‌، حَتَّى أُطْلِقَهُ مِنْ حَبْسِي».</format></p>"
        },
        {
          "paragraphId": 687848279,
          "paragNumber": 10,
          "tocNumber": 0,
          "text": "<p id=\"879\">و في الباب السابق و الآتي ما يدلّ على العنوان.</p>"
        },
        {
          "paragraphId": 687848280,
          "paragNumber": 11,
          "tocNumber": 0,
          "text": "<p id=\"880\"><page number=\"77\"/><heading level=\"2\">باب <format class=\"BM\">الشكوى إلى المؤمن دون غيره </format></heading></p>"
        }
      ],
      "taliqehList": null,
      "footnoteList": null,
      "pageValue": "76",
      "isFreeStudy": true,
      "requestedContentType": "text",
      "providedContentType": "text",
      "isEmpty": false,
      "html": "<div class=\"CODE\">\n  <p id=\"p870\" paragraph-id=\"870\" class=\" G\">\n    <span class=\"hadith\">\n      <span class=\"GPA0 bookPage PageNo76\">76</span>«إِنَّ اَلرَّجُلَ يَقُولُ‌: حُمِمْتُ اَلْيَوْمَ‌، وَ سَهِرْتُ اَلْبَارِحَةَ‌، وَ قَدْ صَدَقَ‌، وَ لَيْسَ هَذَا شَكَاةً‌، وَ إِنَّمَا اَلشَّكْوَى أَنْ يَقُولَ‌: لَقَدِ اُبْتُلِيتُ بِمَا لَمْ يُبْتَلَ بِهِ أَحَدٌ، وَ يَقُولَ‌: لَقَدْ أَصَابَنِي مَا لَمْ يُصِبْ أَحَداً، وَ لَيْسَتِ اَلشَّكْوَى أَنْ يَقُولَ‌: سَهِرْتُ اَلْبَارِحَةَ وَ حُمِمْتُ اَلْيَوْمَ‌، وَ نَحْوَ هَذَا».</span>\n  </p>\n  <p id=\"p871\" paragraph-id=\"871\" class=\" G\">\n    <span class=\"hadith\">\n      <span class=\"sanadHadith\">مَعَانِي اَلْأَخْبَارِ: عَنْ جَعْفَرِ بْنِ مُحَمَّدِ بْنِ مَسْرُورٍ، عَنِ اَلْحُسَيْنِ بْنُ مُحَمَّدِ بْنِ عَامِرٍ، عَنْ عَمِّهِ عَبْدِ اَللَّهِ بْنِ عَامِرٍ، عَنْ مُحَمَّدِ بْنِ أَبِي عُمَيْرٍ:</span> مِثْلَهُ‌.</span>\n  </p>\n  <p id=\"p872\" paragraph-id=\"872\" class=\" G\">\n    <span class=\"hadith\">\n      <span class=\"sanadHadith\">وَ عَنْ أَبِيهِ‌، عَنْ سَعْدٍ، عَنْ أَحْمَدَ بْنِ مُحَمَّدٍ، عَنْ أَبِيهِ‌، عَنْ حَمَّادِ بْنِ عِيسَى، عَنْ رَجُلٍ‌، عَنْ أَبِي عَبْدِ اَللَّهِ (عَلَيْهِ اَلسَّلاَمُ‌) قَالَ‌:</span>\n    </span>\n  </p>\n  <p id=\"p873\" paragraph-id=\"873\" class=\" G\">\n    <span class=\"hadith\">«لَيْسَ اَلشِّكَايَةُ أَنْ يَقُولَ اَلرَّجُلُ‌: مَرِضْتُ اَلْبَارِحَةَ‌، وَ وُعِكْتُ اَلْبَارِحَةَ‌، وَ لَكِنَّ اَلشِّكَايَةَ أَنْ يَقُولَ‌: اُبْتُلِيتُ بِمَا لَمْ يُبْتَلَ بِهِ أَحَدٌ!</span>\n  </p>\n  <p id=\"p874\" paragraph-id=\"874\" class=\" G\">\n    <span class=\"hadith\">\n      <span class=\"sanadHadith\">\n        <span class=\"K\">اَلْكَافِي</span>: <span class=\"G\">اَلْعِدَّةُ‌</span>، عَنْ <span class=\"G\">سَهْلِ بْنِ زِيَادٍ</span>، عَنِ <span class=\"G\">اِبْنِ مَحْبُوبٍ‌</span>، عَنْ <span class=\"G\">عَبْدِ اَلْحَمِيدِ</span>، عَنْ <span class=\"Y\"><span class=\"maasoom\">أَبِي عَبْدِ اَللَّهِ (عَلَيْهِ اَلسَّلاَمُ‌)</span></span>، قَالَ‌:</span>\n    </span>\n  </p>\n  <p id=\"p875\" paragraph-id=\"875\" class=\" G\">\n    <span class=\"hadith\">«إِذَا صَعِدَ مَلَكَا اَلْعَبْدِ اَلْمَرِيضِ إِلَى اَلسَّمَاءِ‌، عِنْدَ كُلِّ مَسَاءٍ‌، يَقُولُ اَلرَّبُّ‌:</span>\n  </p>\n  <p id=\"p876\" paragraph-id=\"876\" class=\" G\">\n    <span class=\"hadith\">«مَا ذَا كَتَبْتُمَا لِعَبْدِي فِي مَرَضِهِ؟».</span>\n  </p>\n  <p id=\"p877\" paragraph-id=\"877\" class=\" G\">\n    <span class=\"hadith\">فَيَقُولاَنِ‌: «اَلشِّكَايَةَ‌».</span>\n  </p>\n  <p id=\"p878\" paragraph-id=\"878\" class=\" G\">\n    <span class=\"hadith\">فَيَقُولُ‌: «مَا أَنْصَفْتُ عَبْدِي أَنْ حَبَسْتُهُ فِي حَبْسٍ مِنْ حَبْسِي ثُمَّ أَمْنَعُهُ اَلشِّكَايَةَ‌! اُكْتُبَا لِعَبْدِي مِثْلَ مَا كُنْتُمَا تَكْتُبَانِ لَهُ مِنَ اَلْخَيْرِ فِي صِحَّتِهِ‌، وَ لاَ تَكْتُبَا عَلَيْهِ سَيِّئَةً‌، حَتَّى أُطْلِقَهُ مِنْ حَبْسِي».</span>\n  </p>\n  <p id=\"p879\" paragraph-id=\"879\" class=\" G\">و في الباب السابق و الآتي ما يدلّ على العنوان.</p>\n  <p id=\"p880\" paragraph-id=\"880\" class=\" G\" />\n</div>",
      "bookPageVisitLogId": "54D905EF-38E7-4108-87A7-F59B3B4949DB",
      "validation": {
        "code": 1,
        "type": "successful",
        "message": "محتوا در دسترس می باشد -  کتاب یا محدوده رایگان"
      }
    }
  ],
  "totalCount": 1,
  "statusCode": 200,
  "message": "OK",
  "exception": null,
  "validationMessages": null
}