{
  "isSuccess": true,
  "data": [
    {
      "pageNumber": 179,
      "sectionNumber": 1,
      "hasTextContent": true,
      "hasImageContent": true,
      "paragList": [
        {
          "paragraphId": 508386495,
          "paragNumber": 1,
          "tocNumber": 0,
          "text": "<p id=\"889\"><page number=\"179\"/><heading level=\"3\">علومه عليه السلام </heading></p>"
        },
        {
          "paragraphId": 508386496,
          "paragNumber": 2,
          "tocNumber": 0,
          "text": "<p id=\"890\">ان معتقدنا نحن الشيعة الامامية فى الامام عليه السلام انه يجب ان يكون اعلم الناس و إورعهم و اتقاهم و افضلهم في كل صفة انسانية و فضيلة روحية و بدنية من علم و اخلاق و تقى و زهد و ما الى ذلك من مكارم الاخلاق</p>"
        },
        {
          "paragraphId": 508386497,
          "paragNumber": 3,
          "tocNumber": 0,
          "text": "<p id=\"891\">و ذلك لان الائمة و هم العترة قرناء القرآن و مترجموه و مفسروا احكامه و مظهروا علومه للناس بعد رسول اللّه «ص».</p>"
        },
        {
          "paragraphId": 508386498,
          "paragNumber": 4,
          "tocNumber": 0,
          "text": "<p id=\"892\">و فى القرآن بلا ريب تبيان كل شىء لا يغادر صغيرة و لا كبيرة الا احصاها فكان من الواجب عقلا و وجدانا ان يكون قرناؤه يعلمون كل ما فيه ليظهروه للناس و يرشدوا اليه و اذا لم يكونوا كذلك عالمين بما فيه فما الفائدة من وجود القرآن بين اظهر الناس و هم لا يدركون مقاصده و لا يعرفون مراميه و معانيه</p>"
        },
        {
          "paragraphId": 508386499,
          "paragNumber": 5,
          "tocNumber": 0,
          "text": "<p id=\"893\">و من هنا كان اوصياء النبي «ص» هم خزان علمه و مبلغى رسالته من بعده قد اصطفاهم اللّه لذلك بعد نبيه و اختارهم لبت الدعوة و ارشاد الخلق بعد رسوله «ص».</p>"
        },
        {
          "paragraphId": 508386500,
          "paragNumber": 6,
          "tocNumber": 0,
          "text": "<p id=\"894\">لذلك تجد مدرسة الامام ابى عبد اللّه الصادق عليه السلام هي الجامعة الاسلامية الكبرى التي تفد اليها رواد العلوم و طلاب الحقيقة من كل حدب و صوب لينتهلوا من قراتها العذب ما يبرد غليل الصادى منهم و يروى عطش الظامى من حديث و فقه و تفسير و اخلاق و كلام و طب و كيميا و نجوم و غيرها<page number=\"180\"/> من كل ما تطلبه رواد العلوم و طلاب المعارف.</p>"
        }
      ],
      "taliqehList": null,
      "footnoteList": null,
      "pageValue": "179",
      "isFreeStudy": true,
      "requestedContentType": "text",
      "providedContentType": "text",
      "isEmpty": false,
      "html": "<div class=\"CODE\">\n  <p id=\"p889\" paragraph-id=\"889\" class=\" G\">\n    <span class=\"GPA0 bookPage PageNo179\">179</span>\n    <strong style=\"0\" class=\"h-3 03\">علومه عليه السلام </strong>\n  </p>\n  <p id=\"p890\" paragraph-id=\"890\" class=\" G\">ان معتقدنا نحن الشيعة الامامية فى الامام عليه السلام انه يجب ان يكون اعلم الناس و إورعهم و اتقاهم و افضلهم في كل صفة انسانية و فضيلة روحية و بدنية من علم و اخلاق و تقى و زهد و ما الى ذلك من مكارم الاخلاق</p>\n  <p id=\"p891\" paragraph-id=\"891\" class=\" G\">و ذلك لان الائمة و هم العترة قرناء القرآن و مترجموه و مفسروا احكامه و مظهروا علومه للناس بعد رسول اللّه «ص».</p>\n  <p id=\"p892\" paragraph-id=\"892\" class=\" G\">و فى القرآن بلا ريب تبيان كل شىء لا يغادر صغيرة و لا كبيرة الا احصاها فكان من الواجب عقلا و وجدانا ان يكون قرناؤه يعلمون كل ما فيه ليظهروه للناس و يرشدوا اليه و اذا لم يكونوا كذلك عالمين بما فيه فما الفائدة من وجود القرآن بين اظهر الناس و هم لا يدركون مقاصده و لا يعرفون مراميه و معانيه</p>\n  <p id=\"p893\" paragraph-id=\"893\" class=\" G\">و من هنا كان اوصياء النبي «ص» هم خزان علمه و مبلغى رسالته من بعده قد اصطفاهم اللّه لذلك بعد نبيه و اختارهم لبت الدعوة و ارشاد الخلق بعد رسوله «ص».</p>\n  <p id=\"p894\" paragraph-id=\"894\" class=\" G\">لذلك تجد مدرسة الامام ابى عبد اللّه الصادق عليه السلام هي الجامعة الاسلامية الكبرى التي تفد اليها رواد العلوم و طلاب الحقيقة من كل حدب و صوب لينتهلوا من قراتها العذب ما يبرد غليل الصادى منهم و يروى عطش الظامى من حديث و فقه و تفسير و اخلاق و كلام و طب و كيميا و نجوم و غيرها</p>\n</div>",
      "bookPageVisitLogId": "0907A752-F0E0-4AE7-8C4F-5487864E7EF0",
      "validation": {
        "code": 1,
        "type": "successful",
        "message": "محتوا در دسترس می باشد -  کتاب یا محدوده رایگان"
      }
    }
  ],
  "totalCount": 1,
  "statusCode": 200,
  "message": "OK",
  "exception": null,
  "validationMessages": null
}